eltakobus
