Metadata-Version: 2.1
Name: eltakobus
Version: 0.0.3
Summary: Library for participating in the Eltako Series 14 RS485 bus
Home-page: https://gitlab.com/chrysn/eltakobus
Author: chrysn
Author-email: chrysn@fsfe.org
License: UNKNOWN
Platform: UNKNOWN
Classifier: Programming Language :: Python :: 3
Provides-Extra: coap
Provides-Extra: eltakotool
Provides-Extra: serial
